{
  "personalInfo": {
    "myimg": "profilePic.jpg",
    "fname": "Shubham",
    "mname": "Parashram",
    "lname": "Sawant",
    "nick": "moghya",
    "address": {
      "list": [
        "Gupta Layout, Mahakali road, Washim, District-Washim, Maharashtra, India 444505 ",
        "'OM' Jaihind colony, Vishrambag, Sangli District-Sangli, Maharashtra, India 416415"
      ]
    },
    "email": "sawantshubham571@gmail.com",
    "mob": "+91 0000 000 000"
  },
  "educations": [
    {
      "periodStart": "July 2014",
      "periodEnd": "May 2018",
      "course": "B.Tech Information Technology",
      "score": "7.59 CGPA",
      "inst": "Walchand College of Engineering, Sangli",
      "board": "Shivaji University",
      "courses": [
        {
          "courseCode": "3IT202",
          "courseName": "Data Structures",
          "courseScore": "9/10",
          "sn": 1
        },
        {
          "courseCode": "3IT304",
          "courseName": "Computer Algorithms",
          "courseScore": "7/10",
          "sn": 2
        },
        {
          "courseCode": "3IT331",
          "courseName": "Machine Learning",
          "courseScore": "10/10",
          "sn": 3
        },
        {
          "courseCode": "3OE---",
          "courseName": "Data Analytics",
          "courseScore": "8/10",
          "sn": 4
        },
        {
          "courseCode": "3IT211",
          "courseName": "Theory of Computation",
          "courseScore": "8/10",
          "sn": 5
        },
        {
          "courseCode": "3IT201",
          "courseName": "Discrete Mathemactics",
          "courseScore": "7/10",
          "sn": 6
        },
        {
          "courseCode": "3IT303",
          "courseName": "Operating System",
          "courseScore": "8/10",
          "sn": 10
        },
        {
          "courseCode": "3IT322",
          "courseName": "Unix Operating System",
          "courseScore": "8/10",
          "sn": 11
        },
        {
          "courseCode": "3IT301",
          "courseName": "Database Engineering",
          "courseScore": "9/10",
          "sn": 12
        },
        {
          "courseCode": "3IT321",
          "courseName": "Advanced Database Engineering",
          "courseScore": "9/10",
          "sn": 13
        },
        {
          "courseCode": "3IT204",
          "courseName": "Data Communication and Networking",
          "courseScore": "7/10",
          "sn": 15
        },
        {
          "courseCode": "3IT213",
          "courseName": "Computer and Wireless Networks",
          "courseScore": "6/10",
          "sn": 16
        },
        {
          "courseCode": "3IT263",
          "courseName": "Computer and Wireless Networks Lab",
          "courseScore": "8/10",
          "sn": 34
        },
        {
          "courseCode": "3IT212",
          "courseName": "Computer Organization and Architechture",
          "courseScore": "7/10",
          "sn": 18
        },
        {
          "courseCode": "3IT372",
          "courseName": "Parallel Programming Lab",
          "courseScore": "10/10",
          "sn": 32
        },
        {
          "courseCode": "3IT324",
          "courseName": "Information Storage and Management",
          "courseScore": "6/10",
          "sn": 21
        },
        {
          "courseCode": "3MA204",
          "courseName": "Linear Algebra",
          "courseScore": "7/10",
          "sn": 7
        },
        {
          "courseCode": "3MA215",
          "courseName": "Statistics and Fuzzy Systems",
          "courseScore": "6/10",
          "sn": 8
        },
        {
          "courseCode": "3IT252",
          "courseName": "Data Structures Lab",
          "courseScore": "10/10",
          "sn": 29
        },
        {
          "courseCode": "3IT203",
          "courseName": "Processor Architechture",
          "courseScore": "7/10",
          "sn": 17
        },
        {
          "courseCode": "3IT281",
          "courseName": "Mini Project - I",
          "courseScore": "10/10",
          "sn": 22
        },
        {
          "courseCode": "3IT214",
          "courseName": "System Programming",
          "courseScore": "7/10",
          "sn": 19
        },
        {
          "courseCode": "3IT255",
          "courseName": "Programming Lab - I (C++)",
          "courseScore": "10/10",
          "sn": 26
        },
        {
          "courseCode": "3IT352",
          "courseName": "Web Technology Lab",
          "courseScore": "9/10",
          "sn": 33
        },
        {
          "courseCode": "3IT342",
          "courseName": "Mini Project - IV",
          "courseScore": "10/10",
          "sn": 25
        },
        {
          "courseCode": "3IT341",
          "courseName": "Mini-Project - III",
          "courseScore": "10/10",
          "sn": 24
        },
        {
          "courseCode": "3IT302",
          "courseName": "Software Engineering Design",
          "courseScore": "7/10",
          "sn": 20
        },
        {
          "courseCode": "3IT371",
          "courseName": "Unix Operating System Lab",
          "courseScore": "10/10",
          "sn": 30
        },
        {
          "courseCode": "3IT282",
          "courseName": "Mini Project - II",
          "courseScore": "10/10",
          "sn": 23
        },
        {
          "courseCode": "3IT265",
          "courseName": "Programming Lab - II (Java)",
          "courseScore": "10/10",
          "sn": 27
        },
        {
          "courseCode": "3IT312",
          "courseName": "Cloud Computing",
          "courseScore": "7/10",
          "sn": 14
        },
        {
          "courseCode": "3IT323",
          "courseName": "Information Theory",
          "courseScore": "8/10",
          "sn": 9
        },
        {
          "courseCode": "2IT253",
          "courseName": "Processor Architechture Lab",
          "courseScore": "10/10",
          "sn": 28
        },
        {
          "courseCode": "3IT351",
          "courseName": "Database Engineering Lab",
          "courseScore": "10/10",
          "sn": 31
        }
      ]
    },
    {
      "periodStart": "April 2013",
      "periodEnd": "May 2014",
      "course": "All India Senior School Examination",
      "score": "89.4%",
      "inst": "Jawahar Navodaya Vidyalaya,Washim",
      "board": "CBSE Chennai",
      "courses": [
        {
          "courseCode": "041",
          "courseName": "Mathemactics",
          "courseScore": "86/100",
          "sn": 1
        },
        {
          "courseCode": "042",
          "courseName": "Physics",
          "courseScore": "87/100",
          "sn": 2
        },
        {
          "courseCode": "043",
          "courseName": "Chemistry",
          "courseScore": "86/100",
          "sn": 3
        },
        {
          "courseCode": "083",
          "courseName": "Computer Science",
          "courseScore": "94/100",
          "sn": 4
        }
      ]
    },
    {
      "periodStart": "April 2011",
      "periodEnd": "May 2012",
      "course": "All India Secondary School Examination",
      "score": "10.00 CGPA",
      "inst": "Jawahar Navodaya Vidyalaya,Washim",
      "board": "CBSE Chennai",
      "courses": [
        {
          "courseCode": "041",
          "courseName": "Mathemactics",
          "courseScore": "10/10",
          "sn": 1
        },
        {
          "courseCode": "086",
          "courseName": "Science",
          "courseScore": "10/10",
          "sn": 2
        }
      ]
    }
  ],
  "skills": [
    {
      "sn": 1,
      "name": "C++",
      "icon": "M117.5 33.5l.3-.2c-.6-1.1-1.5-2.1-2.4-2.6l-48.3-27.8c-.8-.5-1.9-.7-3.1-.7-1.2 0-2.3.3-3.1.7l-48 27.9c-1.7 1-2.9 3.5-2.9 5.4v55.7c0 1.1.2 2.3.9 3.4l-.2.1c.5.8 1.2 1.5 1.9 1.9l48.2 27.9c.8.5 1.9.7 3.1.7 1.2 0 2.3-.3 3.1-.7l48-27.9c1.7-1 2.9-3.5 2.9-5.4v-55.8c.1-.8 0-1.7-.4-2.6zm-35.5 32.5v-4h5v-5h5v5h5v4h-5v5h-5v-5h-5zm3.3-14c-4.2-7.5-12.2-12.5-21.3-12.5-13.5 0-24.5 11-24.5 24.5s11 24.5 24.5 24.5c9.1 0 17.1-5 21.3-12.4l12.9 7.6c-6.8 11.8-19.6 19.8-34.2 19.8-21.8 0-39.5-17.7-39.5-39.5s17.7-39.5 39.5-39.5c14.7 0 27.5 8.1 34.3 20l-13 7.5zm29.7 14h-5v5h-4v-5h-6v-4h6v-5h4v5h5v4z"
    },
    {
      "sn": 2,
      "name": "Python",
      "icon": "M49.33 62h29.159c8.117 0 14.511-6.868 14.511-15.019v-27.798c0-7.912-6.632-13.856-14.555-15.176-5.014-.835-10.195-1.215-15.187-1.191-4.99.023-9.612.448-13.805 1.191-12.355 2.181-14.453 6.751-14.453 15.176v10.817h29v4h-40.224000000000004c-8.484 0-15.914 5.108-18.237 14.811-2.681 11.12-2.8 17.919 0 29.53 2.075 8.642 7.03 14.659 15.515 14.659h9.946v-13.048c0-9.637 8.428-17.952 18.33-17.952zm-1.838-39.11c-3.026 0-5.478-2.479-5.478-5.545 0-3.079 2.451-5.581 5.478-5.581 3.015 0 5.479 2.502 5.479 5.581-.001 3.066-2.465 5.545-5.479 5.545zM122.281 48.811c-2.098-8.448-6.103-14.811-14.599-14.811h-10.682v12.981c0 10.05-8.794 18.019-18.511 18.019h-29.159c-7.988 0-14.33 7.326-14.33 15.326v27.8c0 7.91 6.745 12.564 14.462 14.834 9.242 2.717 17.994 3.208 29.051 0 7.349-2.129 14.487-6.411 14.487-14.834v-11.126h-29v-4h43.682c8.484 0 11.647-5.776 14.599-14.66 3.047-9.145 2.916-17.799 0-29.529zm-41.955 55.606c3.027 0 5.479 2.479 5.479 5.547 0 3.076-2.451 5.579-5.479 5.579-3.015 0-5.478-2.502-5.478-5.579 0-3.068 2.463-5.547 5.478-5.547z"
    },
    {
      "sn": 3,
      "name": "JavaScript",
      "icon": "M2 1v125h125v-125h-125zm66.119 106.513c-1.845 3.749-5.367 6.212-9.448 7.401-6.271 1.44-12.269.619-16.731-2.059-2.986-1.832-5.318-4.652-6.901-7.901l9.52-5.83c.083.035.333.487.667 1.071 1.214 2.034 2.261 3.474 4.319 4.485 2.022.69 6.461 1.131 8.175-2.427 1.047-1.81.714-7.628.714-14.065-.001-10.115.046-20.188.046-30.188h11.709c0 11 .06 21.418 0 32.152.025 6.58.596 12.446-2.07 17.361zm48.574-3.308c-4.07 13.922-26.762 14.374-35.83 5.176-1.916-2.165-3.117-3.296-4.26-5.795 4.819-2.772 4.819-2.772 9.508-5.485 2.547 3.915 4.902 6.068 9.139 6.949 5.748.702 11.531-1.273 10.234-7.378-1.333-4.986-11.77-6.199-18.873-11.531-7.211-4.843-8.901-16.611-2.975-23.335 1.975-2.487 5.343-4.343 8.877-5.235l3.688-.477c7.081-.143 11.507 1.727 14.756 5.355.904.916 1.642 1.904 3.022 4.045-3.772 2.404-3.76 2.381-9.163 5.879-1.154-2.486-3.069-4.046-5.093-4.724-3.142-.952-7.104.083-7.926 3.403-.285 1.023-.226 1.975.227 3.665 1.273 2.903 5.545 4.165 9.377 5.926 11.031 4.474 14.756 9.271 15.672 14.981.882 4.916-.213 8.105-.38 8.581z"
    },
    {
      "sn": 4,
      "name": "PHP",
      "icon": "M64 33.039c-33.74 0-61.094 13.862-61.094 30.961s27.354 30.961 61.094 30.961 61.094-13.862 61.094-30.961-27.354-30.961-61.094-30.961zm-15.897 36.993c-1.458 1.364-3.077 1.927-4.86 2.507-1.783.581-4.052.461-6.811.461h-6.253l-1.733 10h-7.301l6.515-34h14.04c4.224 0 7.305 1.215 9.242 3.432 1.937 2.217 2.519 5.364 1.747 9.337-.319 1.637-.856 3.159-1.614 4.515-.759 1.357-1.75 2.624-2.972 3.748zm21.311 2.968l2.881-14.42c.328-1.688.208-2.942-.361-3.555-.57-.614-1.782-1.025-3.635-1.025h-5.79l-3.731 19h-7.244l6.515-33h7.244l-1.732 9h6.453c4.061 0 6.861.815 8.402 2.231s2.003 3.356 1.387 6.528l-3.031 15.241h-7.358zm40.259-11.178c-.318 1.637-.856 3.133-1.613 4.488-.758 1.357-1.748 2.598-2.971 3.722-1.458 1.364-3.078 1.927-4.86 2.507-1.782.581-4.053.461-6.812.461h-6.253l-1.732 10h-7.301l6.514-34h14.041c4.224 0 7.305 1.215 9.241 3.432 1.935 2.217 2.518 5.418 1.746 9.39zM95.919 54h-5.001l-2.727 14h4.442c2.942 0 5.136-.29 6.576-1.4 1.442-1.108 2.413-2.828 2.918-5.421.484-2.491.264-4.434-.66-5.458-.925-1.024-2.774-1.721-5.548-1.721zM38.934 54h-5.002l-2.727 14h4.441c2.943 0 5.136-.29 6.577-1.4 1.441-1.108 2.413-2.828 2.917-5.421.484-2.491.264-4.434-.66-5.458s-2.772-1.721-5.546-1.721z"
    },
    {
      "sn": 5,
      "name": "MySQL",
      "icon": "M125.477 122.783l-2.616-2.537c-2.479-3.292-5.668-6.184-9.015-8.585-2.669-1.916-8.661-4.504-9.775-7.609l-.205-.195c1.893-.214 4.103-.898 5.85-1.367 2.934-.786 5.356-.583 8.386-1.365 1.366-.39 2.899-.781 3.899-1.171v-.78c-1-1.571-2.427-3.651-4.097-5.073-4.369-3.72-9.041-7.437-13.951-10.537-2.723-1.718-6.041-2.835-8.926-4.292-.971-.491-2.652-.746-3.294-1.562-1.517-1.932-2.328-4.382-3.498-6.633-2.449-4.717-4.849-9.868-7.019-14.831-1.48-3.384-2.443-6.72-4.289-9.756-8.86-14.567-18.395-23.358-33.167-32-3.145-1.838-6.929-2.563-10.929-3.513-2.144-.129-4.291-.26-6.437-.391-1.311-.546-2.674-2.149-3.902-2.927-4.896-3.092-17.449-9.817-21.074-.975-2.289 5.581 3.42 11.025 5.462 13.854 1.435 1.982 3.27 4.207 4.293 6.438.675 1.467.79 2.938 1.367 4.489 1.418 3.822 2.651 7.98 4.487 11.511.927 1.788 1.949 3.67 3.122 5.268.718.981 1.95 1.413 2.145 2.927-1.204 1.686-1.273 4.304-1.95 6.44-3.05 9.615-1.898 21.567 2.537 28.683 1.36 2.186 4.566 6.871 8.975 5.073 3.856-1.57 3.226-6.438 4.329-10.732.249-.972-.185-1.688.815-2.341v.195c1 2.341 2.11 4.683 3.282 7.024 2.6 4.187 6.889 8.562 10.798 11.514 2.027 1.531 3.92 4.177 5.92 5.073v-.101h.221c-.507-1-1.302-1.167-1.95-1.804-1.527-1.496-3.226-3.382-4.487-5.097-3.556-4.827-6.698-10.122-9.561-15.622-1.368-2.626-2.557-5.529-3.709-8.201-.443-1.03-.438-2.592-1.364-3.125-1.263 1.958-3.122 3.54-4.099 5.853-1.561 3.696-1.762 8.204-2.341 12.877-.343.122-.19.038-.391.194-2.718-.655-3.672-3.452-4.683-5.853-2.555-6.07-3.029-15.843-.781-22.829.582-1.809 3.211-7.501 2.146-9.172-.508-1.665-2.184-2.63-3.121-3.903-1.161-1.574-2.319-3.646-3.123-5.464-2.091-4.731-3.066-10.044-5.268-14.828-1.053-2.287-2.832-4.602-4.293-6.634-1.617-2.253-3.429-3.912-4.684-6.635-.445-.968-1.051-2.518-.39-3.513.21-.671.507-.951 1.171-1.17 1.133-.873 4.283.29 5.463.779 3.129 1.3 5.741 2.5 8.392 4.256 1.271.844 2.559 1.89 4.097 2.89h1.756c2.747 0 5.824.232 8.391 1.012 4.535 1.379 8.6 3.542 12.292 5.873 11.246 7.102 20.441 17.22 26.732 29.278 1.012 1.942 1.45 3.799 2.341 5.858 1.798 4.153 4.064 8.428 5.853 12.489 1.786 4.053 3.526 8.142 6.05 11.514 1.327 1.772 6.451 2.724 8.78 3.709 1.633.689 4.308 1.409 5.854 2.34 2.953 1.782 5.814 3.904 8.586 5.855 1.384.974 5.64 3.114 5.853 4.878-6.863-.188-12.104.452-16.585 2.341-1.273.537-3.305.552-3.513 2.147.7.733.809 1.829 1.365 2.731 1.069 1.73 2.876 4.052 4.488 5.268 1.762 1.33 3.576 2.751 5.464 3.902 3.359 2.047 7.107 3.217 10.341 5.268 1.906 1.21 3.958 2.733 5.815 4.097.92.675.891 1.724 2.891 2.147v-.194c-.999-.795-.946-1.893-1.522-2.728zM29.514 23.465c-1.431-.027-2.514.157-3.514.389v.146h.198c.683 1 1.888 2.33 2.731 3.538l1.952 4.108.193-.187c1.209-.853 1.763-2.211 1.756-4.291-.483-.509-.556-1.146-.974-1.754-.558-.809-1.639-1.268-2.342-1.949z"
    },
    {
      "sn": 6,
      "name": "MongoDB",
      "icon": "M90.491 57.282c-.37-4.79-1.496-9.409-3.062-13.934-3.244-10.104-8.45-19.046-15.783-26.74-1.854-1.946-3.916-3.729-5.209-6.151-.818-1.532-1.597-3.085-2.394-4.629l-.505-1.273c-.085.292-.139.396-.142.501-.065 2.517-1.491 4.224-3.267 5.817-1.997 1.793-3.856 3.739-5.775 5.618-1.968 2.588-3.935 5.176-5.901 7.763-1.592 2.925-3.182 5.85-4.772 8.775l-3.19 8.617-.096.134c-1.756 5.768-2.622 11.698-3.048 17.688-.16 2.251.022 4.535.149 6.798.181 3.235.743 6.415 1.586 9.545 3.062 11.372 9.276 20.805 17.771 28.819 1.579 1.489 3.199 2.843 4.847 4.26.282-.965.507-1.93.763-2.895.256-.961.515-1.917.688-2.881-.174.964-.369 1.92-.562 2.881l-.826 2.895.738 2.501.684 3.884.326 4.053c-.003.823-.036 1.648.014 2.47.012.21.288.404.442.606l1.376.483 1.434.558-.246-3.603-.011-3.548.495-5.405.359-1.177 1.027-1.82c1.268-1.02 2.629-1.946 3.784-3.081 2.09-2.054 4.175-4.134 6.045-6.383 2.427-2.917 4.515-6.101 6.191-9.516 1.122-2.284 2.178-4.614 3.052-7.001.77-2.104 1.247-4.315 1.854-6.479.054-.156.126-.309.16-.468 1.254-5.841 1.465-11.741 1.004-17.682zm-23.599 49.375l-.805-1.763.805 1.763 1.183 1.01-1.183-1.01"
    },
    {
      "sn": 7,
      "name": "Apache",
      "icon": "M127.6 75.9l-.3-.5-.2-.1v-.4l-.1-.4-.2-.3-.4-.2h-.1l-.1-.2-.3-.2-.3-.2-.4-.1h-.2l-.4-.4-.5-.3-.6-.3-.6-.2h-.2l-.5-.6-.6-.4-.6-.3-.6-.2h-.1l-.6-.4-.8-.3-.5-.1-.5-.4-.5-.2-.5-.1-.5-.1h-.5l-.6.1h-.1l-.4-.6-.6-.4-.8-.2h-.9l-1 .2-.4.1-.8-.3-.8-.2h-2.6000000000000005l-1-.4-.9-.3-.9-.1h-.6l-.8-.8-.9-.6-.8-.4-.8-.2h-.8l-.4.3-.5-.4-.6-.3-.7-.1-.6.1-.7-.3-.7-.2h-1l-1.1-.4-1.2-.3-1.1-.1h-.2l-1.2-.7-1.2-.3h-1.1.1l-1.7-.4-1.1-.1h-.5l-.7-.7-.8-.5-.9-.2-.9.1-.6.2-.8-.1h-1.8000000000000003v-.2l-1.4-.3-1.4-.2-1.3-.1-.5.1v-.1l-1-.1-1-.1h-.1l-1.1-.5-1.1-.3-1-.1h-.8l-1.1-.4-.9-.2h-1l-1.1-.8-.9-.3-.7-.1-.8-.4-1.2-.2h-1.1l-1.1-.5-1-.2h-.6l-1.2-.6-1-.3-1-.1-.3.1h.1l-1.4-.8-1.1-.4-1-.1h-.1l-.7-.5-.6-.3-.6-.2-.7-.1-.7.1-.8-.6-.7-.3-.9-.1h-.8l-.9.2-.2.1-1-.5-1-.3h-.9l-.8-.5-.7-.3h-.8l-.7.1-.7.2h-.1l-.7-.7-.6-.4-.7-.1-.7.1-.6.3-.2-.1-.3-.2-.3-.1-.3-.1h-.7l-.3.1-.5.3-.1.1-.9-.2h-.8l-.7.2-.6.5-.4.5-.3.7-.3.8-.2.8-.1.8-.1 1.6.1 1.8v.3c-.5-.2-1-.4-1.6-.6v-.4l.1-.6.1-1.3.1-1.2-.1-1.2-.1-.6-.1-.5-.1-.5-.2-.5-.2-.4-.3-.4-.3-.4-.6-.5.2.9.1.6.1.6.1.5.1.6.1.5v.1-.1l-.1-.3-.1-.3-.2-.6-.3-1-.1-.3-.2-1.3v-.4l.1-.7.1-.3.2-.7h-.2l-.5.6-.3.7-.3.7-.1.6v1.4l.1.7.1.7-.1-.1-.3-.4-.3-.4-.2-.5-.2-.5-.2-.5-.1-.7-.1-1-.7.6-.3.6-.2.6v.6l.1.6.2.6.3.6.1.2-.2.2-.6-.1-.1.2.4.2.4.3 1 .8.3.3.5.6.5.5.5.5.4.4.3.4.2.2c-5.7-2.3-11.7-5-19.1-8.5l-.4-.2.2.4c1 1.7 3.9 3.4 6.4 5 1.2.7 2.3 1.4 3.1 2 2.4 1.3 5.6 2.7 8.4 3.8h-.2l-2 .4-1.4.3-1.4.5-.7.3-.7.2-.6.4-.5.4-.5.5-.4.5-.3.6-.2.7.2.1.2-.2.5-.5.2-.2.6-.4.3-.2.3-.2.6-.3.4-.1.3-.1.7-.2.7-.1.6-.2 1.3-.7.6-.4.6-.4.5-.3.4-.2.3-.1.6.2-2.4 1.2-1.3.8-.7.5-.6.5-.6.5-.5.6-.3.5-.2.6-.1.6.1.7.4.9.5-1 .4-.6.4-.5.4-.4.4-.3.9-.6.4-.2-.1.4-.2.8v.9l.1 1 .3 1.1h.2l.2-1.1.3-1 .2-.5.4-.9.5-.9.8-1.4 1.1-1.8c.4.2.8.3 1.2.4l-.1.2-.7 1.4-.4.6-.3.7-.1.7-.2.7-.1.7v.7l.1.6.3.6.5.5.7.4.8.3.3.6.4.5.4.4.4.3.4.2.4.1h1v.1l.4.6.6.5.7.3h.8l.8-.2.2.2.6.6.6.4.7.3.8.1h.6l.6.4.7.3.8.2.6.5.8.4 1 .2 1.1.1h.2l.7.6.8.4.7.3.8.1.9-.2.4.2.6.3.6.1h.6l.6-.1.3.2 1 .3 1.1.1 1.3-.1.4.2.9.3 1 .1 1.4-.1h.1l.9.3 1 .1 1.1-.1.4.3 1 .4 1 .1 1.1-.1v-.1l.6.2h1l1.1-.2.7.2h.8l.8-.1 1.1.2.3.2 1 .3 1 .2 1.1.1 1.1-.1v-.1l.6.2.9.1.9.1v-.1l.6.2 1.2.4 1.3.3 1.4-.3v-.1h.2l.9.2.8.1h.9l.1.1.8.6.8.4h1.3l.8-.4.7-.6.9.1 1.1-.1h1.2v.1l.3.2 1.1.2 1.1-.1 1.1-.5h1l1.2.1 1-.1.6.1h1.4l.9-.1.5.2.6.1.6-.1.6-.3.1.1.8.1h2.5l.8-.3 1.1-.4h1.6l.8-.1.5.2.8.2.8.1.8-.1.9-.2.2.1.9.4.8.3h.8l.6-.3.5-.5.3.1.5.1.5.1h.5l.5-.1.5-.2.7.1.8-.1.7-.3h.7l.6-.1.6-.3.5-.4.1-.1.6.1.6-.1.5.1h.8999999999999999l.4-.3.3-.2.1-.2h.1l.3-.1.3-.2.2-.5.1-.6h.2l.3-.1.1-.3.1.1v-.7zm-107-16.3l.2-.5.3.1-.2.2-.3.2zm.6-6.8l.1.5.1.5.1.5.3 1.6.2.7-.4-.2h.1l-.2-.1-.5-.4v-2.4l.1-.8.1.1z"
    },
    {
      "sn": 8,
      "name": "Git",
      "icon": "M124.737 58.378l-55.116-55.114c-3.172-3.174-8.32-3.174-11.497 0l-11.444 11.446 14.518 14.518c3.375-1.139 7.243-.375 9.932 2.314 2.703 2.706 3.461 6.607 2.294 9.993l13.992 13.993c3.385-1.167 7.292-.413 9.994 2.295 3.78 3.777 3.78 9.9 0 13.679-3.78 3.78-9.901 3.78-13.683 0-2.842-2.844-3.545-7.019-2.105-10.521l-13.048-13.048-.002 34.341c.922.455 1.791 1.063 2.559 1.828 3.778 3.777 3.778 9.898 0 13.683-3.779 3.777-9.904 3.777-13.679 0-3.778-3.784-3.778-9.905 0-13.683.934-.933 2.014-1.638 3.167-2.11v-34.659c-1.153-.472-2.231-1.172-3.167-2.111-2.862-2.86-3.551-7.06-2.083-10.576l-14.313-14.313-37.792 37.79c-3.175 3.177-3.175 8.325 0 11.5l55.117 55.114c3.174 3.174 8.32 3.174 11.499 0l54.858-54.858c3.174-3.176 3.174-8.327-.001-11.501z"
    },
    {
      "sn": 9,
      "name": "Django",
      "icon": "M90.9 61.6l.1-2v-.6h-.8c-1.2 0-2.5.3-3.4.9-1.4.8-2.2 2.3-2.2 4.4 0 3 1.5 4.7 4.1 4.7.8 0 1.3-.1 2.3-.4v-4.3l-.1-2.7zM16.3 64.2c0 3.2 1.6 4.9 4.7 4.9.7 0 1 0 2-.2v-9.5c-1-.2-1.2-.3-2-.3-3 0-4.7 1.9-4.7 5.1zM45.9 68.1c0 1.2.7 1.7 2.3 1.7.9 0 1.8-.1 2.8-.3v-4c-4 .4-5.1 1-5.1 2.6zM108.9 59c-2.3 0-3.7 1.9-3.7 5.2 0 3.3 1.3 5.2 3.7 5.2 2.3 0 3.6-1.9 3.6-5.2 0-3.2-1.3-5.2-3.6-5.2zM126 43.9c0-3.8-3.1-6.9-6.9-6.9h-111.2c-3.8 0-6.9 3.1-6.9 6.9v40.1c0 3.9 3.1 7 6.9 7h111.1c3.8 0 6.9-3.1 6.9-6.9v-40.2zm-115.7 20.4c0-6 4-10 10.2-10 1 0 1.6.1 2.6.3v-8.6h6v27c-3 .6-5.3.8-7.7.8-7.3 0-11.1-3.2-11.1-9.5zm27.7 4.2c0 4.7-.2 7-1.2 9-1 1.9-2.1 3.1-4.7 4.4l-5.5-2.6c2.6-1.2 3.7-2.3 4.5-4 .8-1.7.9-3.7.9-8.8v-11.5h6v13.5zm0-16.5h-6v-6h6v6zm18 21.3c-2 .4-5.8.7-8.3.7-5 0-7.1-1.7-7.1-5.6 0-4.2 3.3-6.1 10.3-6.7v-1.3c0-1.1-.5-1.5-2-1.5-2.2 0-5 .6-7 1.8v-4.6c3-1.2 5.1-1.8 7.8-1.8 3 0 4.8.8 5.7 2.4.5.9.5 2 .5 4.5v12.1zm21 .7h-6v-11.8c0-2.3-1-3.1-3.1-3.1-.8 0-1.9.1-2.9.4v14.5h-6v-18.3c4-.9 6.5-1.3 9.4-1.3 3 0 5.4.7 6.7 2 1.3 1.3 1.9 2.6 1.9 5.6v12zm19.3-11.6.7 5.6v1.7c0 5.1-.6 7.5-1.9 9.4-1.8 2.9-5.1 4.3-9.7 4.3-2.3 0-4.5-.3-6.5-1.2v-5.5c2 1.1 4.2 1.6 6.4 1.6 3.9 0 5.6-1.6 5.6-5.3v-.1c-1 .6-2.4.8-3.9.8-5.2 0-8.5-3.4-8.5-8.8 0-6.7 4.9-10.5 13.5-10.5 2.5 0 4.9.3 7.7.8l-2.3 4.3c-1.6-.3 1.3 0-.7-.2m12.1 14.8c-5.9 0-9.6-3.7-9.6-9.7 0-6.2 3.8-10.1 9.8-10.1 5.9 0 9.5 3.7 9.5 9.8.1 6.1-3.7 10-9.7 10z"
    },
    {
      "sn": 10,
      "name": "Ubuntu",
      "icon": "M64 3.246c-33.555 0-60.755 27.2-60.755 60.754 0 33.552 27.2 60.754 60.755 60.754 33.554 0 60.755-27.202 60.755-60.754 0-33.554-27.2-60.754-60.755-60.754zm13.631 20.922c2.242-3.881 7.2-5.21 11.08-2.972 3.88 2.242 5.208 7.2 2.966 11.08-2.238 3.88-7.197 5.208-11.077 2.967-3.877-2.239-5.206-7.198-2.969-11.075zm-13.631 4.595c3.262 0 6.417.453 9.414 1.281.529 3.259 2.463 6.262 5.548 8.042 3.079 1.775 6.642 1.953 9.725.789 5.998 5.898 9.901 13.919 10.47 22.854l-11.558.17c-1.067-12.103-11.222-21.593-23.599-21.593-3.565 0-6.948.792-9.98 2.203l-5.637-10.099c4.708-2.33 10.01-3.647 15.617-3.647zm-41.311 43.349c-4.482 0-8.113-3.632-8.113-8.112 0-4.481 3.63-8.113 8.113-8.113 4.479 0 8.111 3.631 8.111 8.113 0 4.479-3.632 8.112-8.111 8.112zm7.191.722c2.561-2.09 4.2-5.271 4.2-8.834 0-3.565-1.639-6.747-4.2-8.836 2.194-8.489 7.475-15.738 14.571-20.483l5.931 9.934c-6.092 4.287-10.074 11.369-10.074 19.385s3.981 15.098 10.074 19.383l-5.931 9.937c-7.099-4.744-12.38-11.995-14.571-20.486zm58.831 33.964c-3.879 2.241-8.838.912-11.077-2.969-2.241-3.877-.911-8.835 2.969-11.076 3.877-2.239 8.838-.908 11.077 2.969 2.24 3.88.91 8.839-2.969 11.076zm-.024-17.673c-3.083-1.166-6.645-.991-9.725.788-3.084 1.783-5.019 4.782-5.547 8.042-2.998.83-6.153 1.284-9.415 1.284-5.607 0-10.909-1.318-15.616-3.649l5.636-10.1c3.032 1.411 6.415 2.204 9.98 2.204 12.378 0 22.532-9.488 23.596-21.592l11.561.169c-.569 8.935-4.472 16.956-10.47 22.854z"
    },
    {
      "sn": 11,
      "name": "HTML5",
      "icon": "M9.032 2l10.005 112.093 44.896 12.401 45.02-12.387 10.015-112.107h-109.936zm89.126 26.539l-.627 7.172-.276 3.289h-52.665000000000006l1.257 14h50.156000000000006l-.336 3.471-3.233 36.119-.238 2.27-28.196 7.749v.002l-.034.018-28.177-7.423-1.913-21.206h13.815000000000001l.979 10.919 15.287 4.081h.043v-.546l15.355-3.875 1.604-17.579h-47.698l-3.383-38.117-.329-3.883h68.939l-.33 3.539z"
    },
    {
      "sn": 12,
      "name": "jQuery",
      "icon": "M65.283 106.928c-.828-.187-1.633-.446-2.441-.685l-.609-.185c-.79-.242-1.573-.497-2.352-.765l-.323-.117c-.698-.245-1.388-.504-2.074-.769l-.582-.229c-.752-.297-1.5-.607-2.238-.931l-.447-.198c-.635-.288-1.263-.578-1.889-.879l-.546-.262c-.491-.239-.977-.493-1.461-.743-.324-.171-.654-.332-.975-.51-.592-.317-1.173-.646-1.751-.982l-.591-.33c-.769-.452-1.529-.921-2.28-1.397l-.615-.41c-.546-.351-1.088-.709-1.623-1.079l-.523-.367c-.516-.365-1.026-.734-1.534-1.109l-.679-.514c-.464-.355-.927-.713-1.384-1.082l-.617-.495c-.581-.479-1.156-.959-1.724-1.453l-.188-.159c-.614-.539-1.217-1.092-1.812-1.647l-.51-.491c-.441-.42-.875-.843-1.302-1.277l-.51-.509c-.543-.556-1.076-1.119-1.599-1.69l-.078-.084c-.553-.604-1.092-1.221-1.621-1.844l-.424-.504c-.395-.475-.785-.956-1.167-1.442l-.427-.532c-.459-.596-.908-1.189-1.347-1.794-12.15-16.574-16.516-39.432-6.804-58.204l-8.611 10.921c-11.029 15.851-9.656 36.476-1.231 53.32.2.404.411.801.617 1.198l.395.759.245.437.439.786c.262.461.53.92.805 1.379l.458.756c.304.491.615.976.934 1.46l.398.614c.438.655.888 1.309 1.352 1.951l.039.05.228.308c.4.553.814 1.099 1.232 1.639l.463.59c.373.469.752.935 1.139 1.399l.435.52c.518.61 1.047 1.217 1.586 1.812l.032.033.062.068c.526.575 1.066 1.137 1.612 1.699l.517.521c.423.426.853.845 1.287 1.262l.526.5c.58.547 1.166 1.083 1.764 1.607l.028.022.307.262c.526.456 1.062.909 1.603 1.353l.664.529c.441.354.887.702 1.336 1.044l.714.543c.495.365.995.724 1.499 1.075l.546.387.15.107c.478.329.967.646 1.456.963l.63.42c.749.474 1.51.943 2.278 1.396l.63.355c.565.326 1.134.646 1.711.959.312.168.632.327.946.488.407.213.811.429 1.225.636l.283.137.501.242c.641.306 1.287.607 1.94.897l.41.184c.748.327 1.502.641 2.263.941l.551.217c.704.271 1.418.539 2.135.791l.268.093c.786.275 1.581.53 2.381.779l.575.172c.814.245 1.618.538 2.458.693 53.339 9.727 68.833-32.053 68.833-32.053-13.014 16.954-36.112 21.426-57.997 16.447zM46.069 63.697c1.195 1.713 2.52 3.751 4.105 5.127.575.633 1.176 1.251 1.79 1.858l.472.465c.596.578 1.202 1.146 1.828 1.698l.074.064.018.018c.693.608 1.408 1.191 2.135 1.767l.484.378c.729.559 1.472 1.107 2.233 1.631l.065.049c.336.232.679.448 1.02.672l.482.319c.544.349 1.096.689 1.656 1.015l.234.136c.483.278.973.552 1.463.818l.521.271c.339.177.678.358 1.024.53l.155.07c.702.346 1.411.68 2.136.995l.472.194c.578.246 1.163.486 1.75.71l.75.275c.533.198 1.068.378 1.608.559l.727.233c.767.238 1.525.539 2.324.672 41.183 6.823 50.69-24.886 50.69-24.886-8.57 12.343-25.168 18.233-42.879 13.635-.787-.207-1.562-.431-2.333-.674l-.7-.227c-.548-.177-1.092-.365-1.632-.562l-.736-.274c-.591-.228-1.176-.462-1.756-.708l-.473-.2c-.727-.316-1.443-.65-2.148-.999-.364-.177-.721-.364-1.078-.548l-.622-.32c-.458-.248-.914-.506-1.363-.77l-.326-.185c-.558-.325-1.106-.661-1.65-1.008l-.498-.332c-.358-.232-.717-.469-1.069-.707-.759-.524-1.497-1.072-2.226-1.628l-.501-.395c-7.752-6.12-13.897-14.486-16.819-23.971-3.062-9.836-2.401-20.878 2.903-29.84l-6.517 9.2c-7.977 11.478-7.543 26.844-1.321 38.983 1.043 2.038 2.216 4.013 3.528 5.892zM89.476 49.498c.339.125.678.237 1.022.354l.451.143c.484.152.966.329 1.467.424 22.739 4.394 28.908-11.669 30.549-14.034-5.403 7.779-14.482 9.646-25.623 6.942-.88-.213-1.848-.531-2.696-.832-1.088-.388-2.16-.83-3.201-1.329-1.979-.951-3.864-2.104-5.612-3.424-9.969-7.565-16.162-21.994-9.657-33.745l-3.52 4.851c-4.702 6.92-5.164 15.514-1.901 23.156 3.441 8.112 10.492 14.475 18.721 17.494z"
    },
    {
      "sn": 13,
      "name": "CSS3",
      "icon": "M8.76 1l10.055 112.883 45.118 12.58 45.244-12.626 10.063-112.837h-110.48zm89.591 25.862l-3.347 37.605.01.203-.014.467v-.004l-2.378 26.294-.262 2.336-28.36 7.844v.001l-.022.019-28.311-7.888-1.917-21.739h13.883l.985 11.054 15.386 4.17-.004.008v-.002l15.443-4.229 1.632-18.001h-32.282999999999994l-.277-3.043-.631-7.129-.331-3.828h34.748999999999995l1.264-14h-52.926l-.277-3.041-.63-7.131-.332-3.828h69.281l-.331 3.862z"
    },
    {
      "sn": 14,
      "name": "Bootstrap",
      "icon": "M75.701 65.603c-2.334-.768-5.694-.603-10.08-.603h-17.621v23h18.844c2.944 0 5.012-.315 6.203-.535 2.099-.376 3.854-1.104 5.264-1.982 1.409-.876 2.568-2.205 3.478-3.881.908-1.676 1.363-3.637 1.363-5.83 0-2.568-.658-4.54-1.975-6.436-1.316-1.896-3.141-2.965-5.476-3.733zM73.282 55.087c2.317-.688 4.064-1.89 5.239-3.487 1.176-1.598 1.763-3.631 1.763-6.044 0-2.286-.549-4.314-1.646-6.054s-2.662-2.413-4.699-3.056c-2.037-.641-5.53-.446-10.48-.446h-15.459v20h16.587c4.042 0 6.939-.38 8.695-.913zM126 18.625c0-9.182-7.443-16.625-16.625-16.625h-91.75c-9.182 0-16.625 7.443-16.625 16.625v91.75c0 9.182 7.443 16.625 16.625 16.625h91.75c9.182 0 16.625-7.443 16.625-16.625v-91.75zm-35.447 66.12c-1.362 2.773-3.047 4.911-5.052 6.415-2.006 1.504-4.521 2.78-7.544 3.548-3.022.769-6.728 1.292-11.113 1.292h-27.844v-69h27.42c5.264 0 9.485.609 12.665 2.002 3.181 1.395 5.671 3.497 7.474 6.395 1.801 2.898 2.702 5.907 2.702 9.071 0 2.945-.8 5.708-2.397 8.308-1.598 2.602-4.011 4.694-7.237 6.292 4.166 1.222 7.37 3.304 9.61 6.248 2.24 2.945 3.36 6.422 3.36 10.432 0 3.227-.681 6.225-2.044 8.997z"
    },
    {
      "sn": 15,
      "name": "Heroku",
      "icon": "M102.1 2h-76.2c-6.6 0-11.9 5.3-11.9 11.9v100.3c0 6.6 5.3 11.9 11.9 11.9h76.3c6.6 0 11.9-5.3 11.9-11.9v-100.3c-.1-6.6-5.4-11.9-12-11.9zm-65.1 106.7v-28.2l14.1 14.1-14.1 14.1zm53 .3h-13.1l.1-.2v-49.4s3.1-11.8-39.7 4.8c-.1.2-.2-45.7-.2-45.7l13.9-.1v29.4s39-15.4 39 11.7v49.5zm-5.2-73h-14.8c5.3-6 10.2-17 10.2-17h15.3s-2.6 7-10.7 17z"
    },
    {
      "sn": 16,
      "name": "Flask",
      "icon": "M38.921,107.423c-4.748-3.736-9.814-7.316-13.275-12.359c-7.286-8.895-12.894-19.189-16.728-30.01 c-2.319-7.035-3.11-14.58-6.1-21.343c-3.125-4.915,0.537-10.281,5.919-11.844c2.393-0.46,6.606-2.723,1.521-1.104 c-4.561,3.346-4.999-3.038-0.324-3.444c3.19-0.421,4.365-3.032,3.273-5.38c-3.425-2.239,8.306-4.691,2.401-8.024 c-6.146-6.633,8.6-7.91,4.961-0.374c-0.87,5.791,10.308-1.066,7.712,5.626c2.637,3.213,9.872,0.733,9.69,5.238 c3.841,0.264,5.158,3.491,8.761,3.742c3.737,1.686,10.508,3.013,11.778,7.225c-3.706,2.934-12.284-6.062-12.699,2.061 c1.12,11.997,0.836,24.355,5.223,35.781c2.075,6.916,7.111,12.359,11.654,17.748c4.349,5.277,10.241,8.996,16.247,12.121 c5.268,2.482,10.943,4.131,16.686,5.164c2.326-1.779,6.438-8.4,10.068-5.609c0.174,3.137-7.204,6.559-0.346,6.211 c4.029-1.217,6.822,3.117,10.141-0.791c3.057,3.617,12.706-2.314,10.531,5.086c-2.942,1.898-7.232,0.754-10.178,3.361 c-4.855-2.424-8.722,2.17-14.102,1.59c-5.967,1.07-12.046,1.5-18.098,1.512c-9.934-0.785-20.073-1.115-29.523-4.574 C48.793,113.485,43.6,110.454,38.921,107.423L38.921,107.423z M47.308,111.058c5.198,2.242,10.28,4.615,15.977,5.33 c9.038,1.256,18.369,3.191,27.438,1.428c-4.104-1.857-8.349,0.719-12.439-1.324c-4.9,1.053-10.166-0.271-15.154-0.928 c-5.667-2.523-11.786-4.258-17.095-7.537c-6.635-2.426,3.431,3.107,5.223,3.555c4.146,2.355-4.561-1.205-5.79-2.182 c-3.473-1.949-3.916-1.541-0.343,0.436C45.843,110.255,46.555,110.696,47.308,111.058L47.308,111.058z M37.418,104.067 c5.038,1.869-0.023-3.539-2.328-3.227c-1.023-1.775-3.907-2.898-1.873-3.848c-3.658,1.271-3.834-4.834-5.553-3.957 c-3.873-1.225-1.506-5.555-6.121-8.217c-0.421-2.803-4.583-5.232-5.907-9.457c-0.585-2.166-4.703-8.377-2.173-2.598 c2.15,5.568,5.937,10.338,9.09,15.1c2.447,4.533,5.337,9.275,9.793,12.102C33.85,101.409,35.297,103.618,37.418,104.067 L37.418,104.067z M22.913,88.138C23.086,87.376,23.831,89.782,22.913,88.138L22.913,88.138z M43.453,106.306 C44.567,105.804,41.849,105.673,43.453,106.306L43.453,106.306z M46.184,107.298C45.902,105.925,44.938,108.071,46.184,107.298 L46.184,107.298z M49.608,108.728C51.236,107.175,47.096,107.749,49.608,108.728L49.608,108.728z M55.474,111.997 C56.464,110.534,52.305,111.446,55.474,111.997L55.474,111.997z M44.211,104.147C46.74,102.507,40.939,104.124,44.211,104.147 L44.211,104.147z M46.777,105.423C46.704,104.56,45.862,105.813,46.777,105.423L46.777,105.423z M59.605,113.433 c2.063,1.303,12.048,2.854,5.797,0.533C64.354,114.19,53.811,110.985,59.605,113.433L59.605,113.433z M39.24,97.567 C39.039,96.704,36.038,96.61,39.24,97.567L39.24,97.567z M45.21,101.054C46.766,99.966,41.984,100.216,45.21,101.054L45.21,101.054z M50.237,104.132C52.465,103.292,46.619,103.288,50.237,104.132L50.237,104.132z M36.806,94.925 c2.422,1.854,9.765,0.238,3.707-1.107c-2.754-1.471-8.962-2.477-4.731,0.885L36.806,94.925L36.806,94.925L36.806,94.925z M53.638,105.194C54.649,103.478,49.409,104.216,53.638,105.194L53.638,105.194z M48.525,101.128 c5.917,1.676-4.977-3.74-1.461-0.611l0.78,0.352L48.525,101.128L48.525,101.128L48.525,101.128z M58.779,107.058 C64.383,107.112,53.715,106.286,58.779,107.058L58.779,107.058L58.779,107.058z M34.651,91.679 C34.431,90.636,33.27,91.769,34.651,91.679L34.651,91.679z M68.258,112.374C68.408,110.491,66.43,113.78,68.258,112.374 L68.258,112.374z M44.216,97.536C43.875,96.544,42.465,97.493,44.216,97.536L44.216,97.536z M35.182,91.024 C38.4,90.831,30.776,89.608,35.182,91.024L35.182,91.024z M24.48,84.108C24.08,82.563,20.979,81.337,24.48,84.108L24.48,84.108z M52.575,101.938C51.988,101.265,52.298,102.085,52.575,101.938L52.575,101.938z M70.061,112.669 C70.006,111.64,69.107,113.058,70.061,112.669L70.061,112.669z M51.027,100.341C51.344,99.017,48.284,99.938,51.027,100.341 L51.027,100.341z M38,92.081C40.396,91.827,34.164,90.464,38,92.081L38,92.081z M60.037,105.778 C63.77,104.298,56.401,105.056,60.037,105.778L60.037,105.778z M48.576,97.997c4.297,0.555-5.117-2.928-0.945-0.313L48.576,97.997 L48.576,97.997L48.576,97.997z M63.517,107.183c4.015-2.396,2.69,5.621,6.811,0.68c4.063-2.971-3.508,3.668,1.498,0.525 c3.622-2.424,8.971,1.15,12.35,2.313c2.429-0.117,4.795,2.102,7.285,0.752c4.797-1.293-9.379-1.916-5.662-4.207 c-4.391,1.275-7.63-1.521-9.791-4.334c-4.922-1.135-10.613-3.648-13.07-8.012c-1.002-1.633,1.446,0.232-0.865-2.441 c-2.965-2.635-4.446-5.633-6.437-8.84c-2.378-1.268-2.659-5.002-2.898-0.121c0.02-3.08-2.873-5.154-3.578-4.295 c-0.012-2.965,3.094-1.48,0.92-3.672c-0.468-3.074-2.01-6.277-2.472-9.744c-0.719-1.675-0.102-5.257-2.458-1.47 c-0.856,4.003-0.284-4.915,1.052-1.978c1.75-3-0.632-2.646-0.727-2.232c1.141-2.53,0.723-6.123-0.299-4.754 c0.61-2.684,0.962-9.878-0.907-8.601c1.132-2.812,2.15-12.846-2.774-9.018c-1.993,0.027-5.447,0.721-7.078,1.533 c5.116,2.823-0.517,1.021-2.603,0.569c-0.271,2.611-2.335,1.485-4.913,1.51c4.121,0.51-2.005,4.214-4.365,2.773 c-3.071,1.464,2.646,5.127,0.061,6.262c0.318,1.704-4.701-0.617-4.309,3.324c-2.979-1.255-0.408,4.675,1.082,2.669 c5.067,1.371,3.567,4.496,3.695,7.467c-0.825,1.728-4.077-4.066-0.724-3.802c-2.645-4.291-2.925-1.552-5.122,0.443 c-0.51,0.146,5.604,2.843,1.767,4.175c3.375,0.519,3.474,3.476,4.162,5.343c2.028,2.115,1.611-2.334,4.041,0.207 c-1.537-2.262-8.139-6.377-2.824-5.059c-0.03-2.276-0.962-4.114,0.668-4.069c1.613-2.921-1.691,7.202,1.945,3.489 c1.006-0.438,1.257-2.922,3.066,0.236c2.627,2.583,0.95,4.457-2.757,2.089c0.662,2.25,4.958,3.051,4.15,6.57 c0.854,3.096,2.054,1.957,3.097,1.779c0.819,3.008,1.284,0.799,1.323-0.637c3.748,0.801,2.869,3.018,4.042,4.566 c2.583,1.166-3.695-7.902,0.737-2.725c4.664,4.211,1.751,5.969-2.436,5.293c2.649-0.211,3.502,3.586,6.817,3.449 c3.022,1.438,5.07,6.959-0.141,4.662c-1.805-1.629-8.203-3.639-2.977-0.539c4.822,2.232,8.655,3.566,13.308,6.371 c3.328,2.377,4.766,5.098,6.026,5.637c-2.798,1.338-8.429-1.066-4.247-1.801c-2.61-0.475-5.546-1.797-3.047,1.453 c2.126,1.777,7.531,1.59,8.502,1.791c-0.822,1.809-2.231,1.951,0.032,2.092C59.949,106.204,63.285,106.415,63.517,107.183 L63.517,107.183z M58.353,92.595c-1.539-1.609-1.936-4.613-0.274-1.996C58.932,90.938,60.806,95.515,58.353,92.595L58.353,92.595 L58.353,92.595z M75.174,103.282C76.133,103.22,75.203,104.013,75.174,103.282L75.174,103.282z M55.926,88.655 C55.865,86.224,56.478,90.53,55.926,88.655L55.926,88.655z M54.253,86.405C52.317,82.671,56.691,87.464,54.253,86.405L54.253,86.405 z M33.987,72.421C35.126,72.118,34.549,74.36,33.987,72.421L33.987,72.421z M50.118,81.161 C50.815,78.538,50.936,83.356,50.118,81.161L50.118,81.161z M38.724,73.239C37.921,71.79,40.403,74.595,38.724,73.239L38.724,73.239 z M48.5,76.37c-1.831-4.102,1.3-2.242,0.408,0.672L48.5,76.37L48.5,76.37L48.5,76.37z M31.64,65.128 c-0.819-1.348-2.171-5.295-1.736-6.502c0.391,1.964,4.175,8.452,1.853,2.688c-2.563-4.829,3.067,1.568,3.646,2.774 c0.271,1.195-1.584-0.327-0.329,2.482C32.786,63.371,33.725,68.335,31.64,65.128L31.64,65.128z M26.43,61.535 C26.643,58.407,27.621,63.681,26.43,61.535L26.43,61.535z M28.773,62.345C29.893,59.983,30.667,65.636,28.773,62.345L28.773,62.345z M23.134,57.984c-1.939-1.932-3.345-3.707,0.091-1.197c1.321,0.049-2.941-4.041,0.32-1.299 C26.971,56.111,25.236,61.105,23.134,57.984L23.134,57.984z M26.094,57.908C27.222,56.789,26.693,59.006,26.094,57.908 L26.094,57.908z M27.92,58.488C26.208,55.29,29.993,59.833,27.92,58.488L27.92,58.488z M24.295,55.028 c-5.639-5.021,7.085,2.623,0.921,0.929L24.295,55.028L24.295,55.028L24.295,55.028z M40.456,64.414 c-2.442-1.462-0.649-10.301,0.186-4.257c2.372-0.768-0.133,3.124,1.635,3.086C42.001,65.696,41.208,66.579,40.456,64.414 L40.456,64.414z M46.434,67.946C46.672,65.282,46.935,69.771,46.434,67.946L46.434,67.946z M45.396,66.921 C45.664,65.786,45.42,68.261,45.396,66.921L45.396,66.921z M25.4,53.377c-3.623-5,10.532,5.056,2.322,1.267 C26.865,54.421,25.832,54.34,25.4,53.377L25.4,53.377z M36.911,59.479C36.568,55.27,37.676,60.178,36.911,59.479L36.911,59.479 L36.911,59.479z M45.652,65.089C46.325,62.689,45.702,66.671,45.652,65.089L45.652,65.089z M25.958,51.47 c2.153-0.462,8.922,3.777,2.707,1.209C27.974,51.917,26.5,52.262,25.958,51.47L25.958,51.47z M44.449,60.685 c0.229-4.304,1.286-2.568,0.009,0.617L44.449,60.685L44.449,60.685L44.449,60.685z M27.561,49.971 c0.879-1.286-2.333-5.816,0.462-1.624c1.206,0.959,3.492,1.605,1.474,2.01C32.67,53.155,28.722,51.116,27.561,49.971L27.561,49.971z M43.535,59.343C44.14,54.439,44.07,62.213,43.535,59.343L43.535,59.343z M25.726,45.443C26.398,45.158,26.082,46.335,25.726,45.443 L25.726,45.443z M29.894,47.923C30.966,45.672,31.871,50.433,29.894,47.923L29.894,47.923z M41.647,54.46 C41.637,53.599,41.869,55.717,41.647,54.46L41.647,54.46z M40.966,52.954C39.335,48.93,42.484,55.085,40.966,52.954L40.966,52.954z M39.964,50.313C39.691,48.651,40.897,52.404,39.964,50.313L39.964,50.313L39.964,50.313z M41.596,47.667 c-1.122-1.97,1.414-8.694,1.697-4.525c-1.182,3.248-0.341,5.063,0.48,0.705C45.296,40.42,43.446,50.616,41.596,47.667L41.596,47.667 L41.596,47.667z M43.272,37.67C43.758,37.069,43.379,38.391,43.272,37.67L43.272,37.67z M40.472,92.8 C39.811,92.22,40.559,93.165,40.472,92.8L40.472,92.8z M46.236,95.712c3.206,0.826,3.19-0.496,0.292-0.891 c-1.556-1.449-6.475-2.986-2.073-0.18C44.746,95.382,45.666,95.362,46.236,95.712L46.236,95.712z M34.855,88.151 c1.764,1.32,6.652,3.732,2.516,0.504c1.395-1.621-2.67-2.486-1.322-3.568c-3.43-2.098-2.708-1.912-0.302-1.844 c-4.121-1.844,0.596-1.705,0.373-2.65c-1.589-0.313-7.894-2.805-4.186,0.205c-3.769-1.922-0.898,0.713-2.037,0.436 c-3.856-1.051,3.433,2.938-0.611,1.947c2.21,1.752,5.951,4.49,0.933,1.854C29.56,85.987,33.813,87.431,34.855,88.151L34.855,88.151z M40.881,91.618C48.209,93.978,37.286,88.728,40.881,91.618L40.881,91.618z M71.738,110.31 C71.834,108.854,70.736,111.552,71.738,110.31L71.738,110.31z M74.91,111.644c1.69-1.637,0.071,2.613,2.802-0.4 c0.029-2.156-0.081-3.43-3.138-0.809C73.728,110.903,73.354,112.886,74.91,111.644L74.91,111.644z M24.567,80.028 C24.048,77.983,20.926,77.997,24.567,80.028L24.567,80.028z M27.952,82.245C26.693,80.157,23.463,80.358,27.952,82.245 L27.952,82.245z M47.219,93.864c1.882,1.674,8.64,1.229,2.285,0.207C48.561,92.681,43.53,93.013,47.219,93.864L47.219,93.864z M73.702,110.224C76.597,107.794,70.898,111.306,73.702,110.224L73.702,110.224z M79.725,114.36 C79.744,113.577,78.478,114.7,79.725,114.36L79.725,114.36z M79.735,113.269C82.941,109.874,76.629,113.468,79.735,113.269 L79.735,113.269L79.735,113.269z M16.237,73.054c-2.732-3.896-1.698-5.65-4.333-8.832c-0.502-2.437-4.522-7.959-2.08-2.111 C12.06,65.534,12.721,70.833,16.237,73.054L16.237,73.054z M78.729,112.188C84.63,108.374,76.31,110.532,78.729,112.188 L78.729,112.188z M83.232,113.952C86.186,111.417,81.362,113.421,83.232,113.952L83.232,113.952z M23.562,75.72 C24.408,74.462,21.38,75.554,23.562,75.72L23.562,75.72z M82.29,112.747c2.862-1.842-0.657-1.557-0.518,0.17L82.29,112.747 L82.29,112.747L82.29,112.747z M43.481,88.288C43.381,87.038,41.969,88.392,43.481,88.288L43.481,88.288z M45.879,89.665 C45.116,88.124,44.708,89.909,45.879,89.665L45.879,89.665z M86.88,113.995c3.665-2.645-2.22-0.508-0.768,0.5L86.88,113.995 L86.88,113.995L86.88,113.995z M85.478,113.317C88.463,110.815,82.326,114.425,85.478,113.317L85.478,113.317z M92.645,118.089 C94.65,116.749,90.211,117.655,92.645,118.089L92.645,118.089z M25.4,74.812c2.685,0.6,10.736,6.611,5.986,0.418 c-2.431-0.721-0.974-6.666-3.455-5.617c1.666,2.783,1.369,3.965-2.127,2.215c-4.391-2.146-2.467,1.061-1.607,1.945 C23.026,74.042,25.745,74.79,25.4,74.812L25.4,74.812z M13.165,65.146c0.479-1.988-4.43-10.938-2.319-4.485 C11.606,62.013,11.527,64.578,13.165,65.146L13.165,65.146z M35.625,78.995C34.243,77.839,35.558,78.831,35.625,78.995 L35.625,78.995z M39.03,79.786C39.03,77.679,35.265,78.931,39.03,79.786L39.03,79.786z M68.548,98.394 C67.984,96.954,66.322,98.362,68.548,98.394L68.548,98.394L68.548,98.394z M69.965,99.429 C69.754,98.622,69.145,99.583,69.965,99.429L69.965,99.429z M81.664,106.8C82.789,105.97,80.26,106.692,81.664,106.8L81.664,106.8z M19.275,66.706C22.494,65.462,15.826,65.817,19.275,66.706L19.275,66.706z M65.949,96.11C65.912,94.026,63.896,96.628,65.949,96.11 L65.949,96.11z M18.004,63.746C20.07,63.048,16.09,63.286,18.004,63.746L18.004,63.746z M24.001,66.649 C23.967,65.966,23.37,66.909,24.001,66.649L24.001,66.649z M97.195,111.534c2.656-0.541,8.719,1.352,9.694-0.705 c-3.229-0.08-11.167-2.281-11.544,0.521l0.708,0.113L97.195,111.534L97.195,111.534L97.195,111.534z M25.91,67.13 C25.958,65.021,24.265,67.05,25.91,67.13L25.91,67.13z M10.135,56.186C9.418,52.167,7.41,55.579,10.135,56.186L10.135,56.186z M13.896,57.133C13.944,55.839,10.452,55.97,13.896,57.133L13.896,57.133z M16.045,58.193 C15.424,57.685,15.561,58.822,16.045,58.193L16.045,58.193z M29.574,66.864C30.212,66.278,28.066,66.435,29.574,66.864 L29.574,66.864z M14.615,55.807C14.25,52.769,10.257,55.352,14.615,55.807L14.615,55.807z M6.899,50.805 C6.793,49.4,6.149,51.332,6.899,50.805L6.899,50.805z M8.051,49.938C7.861,48.274,7.063,50.146,8.051,49.938L8.051,49.938z M14.387,53.718c2.681-1.05-4.881-2.177-0.548-0.198L14.387,53.718L14.387,53.718z M99.23,106.126 C100.945,104.554,97.051,105.638,99.23,106.126L99.23,106.126z M109.479,111.437C110.168,109.405,107.746,111.704,109.479,111.437 L109.479,111.437z M15.035,50.397C15.32,48.43,12.909,50.789,15.035,50.397L15.035,50.397z M6.015,44.354 c-0.484-2.776-0.417-7.653,4.216-6.006c-6.183,1.23,4.284,7.691,2.962,2.588c2.602,0.129,5.089-1.536,3.722,0.988 c5.127-0.563,8.678-5.01,13.629-4.384c3.855-0.514,8.073-0.898,12.228-2.452c3.417-0.245,6.705-3.927,4.835-6.105 c-4.658-0.395-9.539,0.188-14.687,1.214c-5.705,1.184-10.89,3.438-16.647,4.406c-5.614,0.756,1.127,2.077-0.48,2.372 c-2.927,1.017,3.492,1.702-0.38,2.773c-2.391-0.455-4.881-1.277-3.859-3.799c-5.375,0.701-10.103,2.931-5.854,8.4L6.015,44.354 L6.015,44.354L6.015,44.354z M18.972,37.756c1.258-4.642,6.75,3.821,2.064,0.617C20.478,37.952,19.553,37.611,18.972,37.756 L18.972,37.756z M19.216,35.503C21.035,34.151,20.181,36.267,19.216,35.503L19.216,35.503z M21.525,35.542 c0.166-2.136,5.289,1.133,0.844,0.77L21.525,35.542L21.525,35.542L21.525,35.542z M24.682,34.271 C25.839,32.921,25.018,35.47,24.682,34.271L24.682,34.271z M25.494,33.733c1.922-2.311,10.88-1.477,4.324-0.229 C28.06,32.179,26.713,34.284,25.494,33.733L25.494,33.733z M37.185,31.929C36.896,25.62,42.998,34.167,37.185,31.929L37.185,31.929z M40.505,31.909c1.213-3.177,4.709-1.276,0.563-0.638C41.156,31.61,40.944,32.913,40.505,31.909L40.505,31.909z M13.728,48.767 C17.35,46.546,9.881,46.838,13.728,48.767L13.728,48.767L13.728,48.767z M16.408,49.509C17.68,48.16,13.644,48.961,16.408,49.509 L16.408,49.509z M8.511,43.909C10.582,42.316,6.06,43.302,8.511,43.909L8.511,43.909z M115.529,110.858 C115.592,109.011,113.946,111.688,115.529,110.858L115.529,110.858z M104.656,103.437 C104.964,101.312,103.258,103.618,104.656,103.437L104.656,103.437z M118.52,111.573c2.895,0.01,8.772-0.9,2.474-0.898 C120.004,110.829,115.233,110.8,118.52,111.573L118.52,111.573L118.52,111.573z M18.765,48.207c2.344-0.16,3.665-2.583-0.455-2.447 c-6.385-0.657,5.632,2.189-0.819,1.376C16.625,47.706,18.714,48.366,18.765,48.207L18.765,48.207z M20.828,49.25 C20.584,47.747,20.101,50.05,20.828,49.25L20.828,49.25z M23.277,42.724C24.292,41.46,21.869,42.385,23.277,42.724L23.277,42.724z M15.479,29.696c4.186-1.421,9.906-3.019,11.879,0.701c-2.009-2.416-0.813-4.799,1.086-1.262c2.684,3.577,4.028-1.627,2.282-2.829 c1.991,2.472,4.252,3.642,1.333,0.156c3.173-3.815-6.355,0.5-8.519,0.457C22.5,27.387,12.785,29.396,15.479,29.696L15.479,29.696z M17.934,25.004c2.385-1.801,8.25,1.069,4.486-1.793C22.052,22.889,14.181,25.385,17.934,25.004L17.934,25.004z M26.63,25.364 c2.79,0.068-1.203-3.752,2.12-2.021c-0.544-1.783-3.872-2.117-5.499-2.831C22.331,22.143,25.123,25.385,26.63,25.364L26.63,25.364z M19.459,17.467C20.424,16.162,17.765,18.134,19.459,17.467L19.459,17.467z M23.013,18.318c4.5-0.594-1.147-1.936-0.908-0.047 L23.013,18.318L23.013,18.318L23.013,18.318z M16.375,13.126c-3.168-4.133,5.959,0.696,2.738-3.636 C16.406,7.335,13.804,11.922,16.375,13.126L16.375,13.126z M57.024,35.021c1.452-2.574-5.997-3.471-0.978-0.912 C56.509,34.263,56.403,35.199,57.024,35.021L57.024,35.021z"
    }
  ],
  "experince": [
    {
      "sn": 6,
      "link": "",
      "workPosition": "Scout Troop Leader",
      "periodStart": "April 2010",
      "periodEnd": "May 2012",
      "organisation": "JNV,Washim",
      "experience": "It was nice to be a part of Scouting.Arranged camps,hikes and awareness rallies.",
      "type": "volunteer"
    },
    {
      "sn": 5,
      "link": "http://wcepace.in/",
      "workPosition": "Asst. Program Director in Events",
      "periodStart": "April 2015",
      "periodEnd": "March 2016",
      "organisation": "Personality Advancement Circle of Engineers.",
      "experience": "Learnt how to organize professional events and actvites, how to manage resources and make most out of everything.",
      "type": "volunteer"
    },
    {
      "sn": 4,
      "link": "http://wcepace.in/",
      "workPosition": "Joint. Skills Developer",
      "periodStart": "April 2016",
      "periodEnd": "January 2017",
      "organisation": "Personality Advancement Circle of Engineers.",
      "experience": "Good to arrange Meet ups for professional skill development of fellow PACErs.",
      "type": "volunteer"
    },
    {
      "sn": 3,
      "link": "http://wcepace.in/",
      "workPosition": "Cheif. Skills Developer",
      "periodStart": "January 2017",
      "periodEnd": "December 2017",
      "organisation": "Personality Advancement Circle of Engineers.",
      "experience": "Good to arrange Meet ups for professional skill development of fellow PACErs.",
      "type": "volunteer"
    },
    {
      "sn": 2,
      "link": "http://pitchteq.com/",
      "workPosition": "PHP Developer",
      "periodStart": "July 2016",
      "periodEnd": "July 2018",
      "organisation": "PitchTeQ ",
      "experience": "A group of college students established a web solutions startup. Worked on an e-commerce project.",
      "type": "work"
    },
    {
      "sn": 1,
      "link": "http://www.praxisinfotech.com/",
      "workPosition": "Web Development Intern",
      "periodStart": "June 2017",
      "periodEnd": "July 2017",
      "organisation": "Praxis Infotech ",
      "experience": "Developed a PHP, MySQL web application. Added a layer on top of Google maps for places and events.",
      "type": "work"
    },
    {
      "sn": 0,
      "link": "https://www.media.net/",
      "workPosition": "Software Development Engineer",
      "periodStart": "July 2018",
      "periodEnd": "Feb 2020",
      "organisation": "Media.Net",
      "experience": "<ul><li>Involved in designing, developing features and parts of an App Distribution platform.</li><li>Majorly my work involves:</li><ul><li>– Designing, writing and consuming HTTP-REST APIs.</li><li>– Setting up job queues for multiple monitoring tasks.</li><li>– Writing template code for full-stack Web and Desktop applications.</li><li>– Automating and setting up application build processes.</li><li>– Extensive research and POC creation of features,solutions for novel business requirements.</li><li>– Identifying bottlenecks across system and optimize database queries, page load time, serving time, build time.</li></ul><li>Developed node-js, python back-end applications for automating and monitoring application build processes.</li><li>Developed node-js module for restructuring and renaming directory tree, handled resolution of interlinked file-paths in files.</li><li>Developed macOs desktop application(A Safari App Extension) using Swift for search monetization with app installer and app auto update feature from scratch</li></ul>",
      "type": "work"
    },
    {
      "sn": -1,
      "link": "https://www.cohesity.com",
      "workPosition": "Member of Technical Staff",
      "periodStart": "Feb 2020",
      "periodEnd": "Present",
      "organisation": "Cohesity",
      "experience": "<ul><li>\nDevelopingdistributedsystemsoftwareusingC++,Golangfordataprotection.</li></ul>",
      "type": "work"
    }
  ],
  "projects": [
    {
      "sn": 14,
      "projectTitle": "Traffic Rules",
      "periodStart": "July 2015",
      "periodEnd": "Nov 2015",
      "toolsUsed": [
        "Blender",
        "Movie Maker"
      ],
      "tags": [
        "blender",
        "animation",
        "3d-modelling",
        "traffic rules"
      ],
      "shortInfo": "Its a 3D animation video made using Blender Tool for spreading awareness regarding Traffic rules. Mini project for semester III.",
      "link": "https://github.com/moghya/Traffic-Rules"
    },
    {
      "sn": 13,
      "projectTitle": "Smart Hospital Management",
      "periodStart": "Aug 2015",
      "periodEnd": "Sep 2015",
      "toolsUsed": [
        "c++",
        "qt"
      ],
      "tags": [
        "oop",
        "c++",
        "qt",
        "gui",
        "files"
      ],
      "shortInfo": "C++ Qt Standalone Application keeps track of every patient and its visits. Data collected can be used for Projects of Data Mining and Machine Learning as data sets.",
      "link": "https://github.com/moghya/smartHMS"
    },
    {
      "sn": 12,
      "projectTitle": "Seat Allocation",
      "periodStart": "Dec 2015",
      "periodEnd": "Dec 2015",
      "toolsUsed": [
        "c++"
      ],
      "tags": [
        "c++",
        "gayle-shapely",
        "ds",
        "oop"
      ],
      "shortInfo": "Simulation of college seat allocation process. Choice filling and Seat Allocation are performed. Modified Gayle-Shapely Algorithm implemented. Can be scaled using C++ CGI for deployment.",
      "link": "https://github.com/moghya/collegeSeatAllocationPrototype"
    },
    {
      "sn": 11,
      "projectTitle": "Online External Examination Portal",
      "periodStart": "Feb 2016",
      "periodEnd": "May 2016",
      "toolsUsed": [
        "php",
        "js",
        "mysql",
        "html",
        "css",
        "bootstrap"
      ],
      "tags": [
        "php",
        "js",
        "bootstrap",
        "mysql"
      ],
      "shortInfo": "It's a web application developed using PHP , MySQL, Bootstrap, JavaScript etc. for conducting practical exams online.",
      "link": "https://github.com/moghya/external-exam-portal"
    },
    {
      "sn": 9,
      "projectTitle": "LookIn",
      "periodStart": "Mar 2016",
      "periodEnd": "May 2016",
      "toolsUsed": [
        "python",
        "sqllite3",
        "beautifulsoup",
        "requests"
      ],
      "tags": [
        "search engine",
        "python",
        "indexing",
        "web scraping"
      ],
      "shortInfo": "It's a search engine made using Python, Beautifulsoup . Which crawls downloaded websites and indexes them. After one time indexing it delivers search results ",
      "link": ""
    },
    {
      "sn": 3,
      "projectTitle": "dsalglib ",
      "periodStart": "May 2016",
      "periodEnd": "Present",
      "toolsUsed": [
        "c++"
      ],
      "tags": [
        "ds",
        "algo",
        "template",
        "c++"
      ],
      "shortInfo": "Its a ready to use data structures and algorithms c++ template library.Many useful data structures and algorithms are implemented . One should just focus on his/her project necessity and dsalglib will take care of data structures and algorithms.",
      "link": "http://moghya.me/dsalglib/"
    },
    {
      "sn": 1,
      "projectTitle": "Strategic Location using Facebook Data",
      "periodStart": "Dec 2016",
      "periodEnd": "Dec 2016",
      "toolsUsed": [
        "python",
        "scikit-learn",
        "ipynb",
        "graph-api"
      ],
      "tags": [
        "machine-learning",
        "regression",
        "python"
      ],
      "shortInfo": "Choosing optimal location for business using data from social media websites contribute largely to the profit.Our System helps business choose optimal location for higher number of check-ins .indirectly helping businesses to increase their profits.We have used to machine learning techniques to help improve our system.",
      "link": "https://github.com/moghya/Stratergic-Location"
    },
    {
      "sn": 2,
      "projectTitle": "prowessIndex",
      "periodStart": "June 2017",
      "periodEnd": "June 2017",
      "toolsUsed": [
        "python",
        "flask",
        "pandas"
      ],
      "tags": [
        "python",
        "data analytics"
      ],
      "shortInfo": "This is a simple flask web app implementation of a paper that I'm writing 'Making Sense of Numbers'. This paper proposes method for deriving inferences about prowessness of a stduent using attained graded.",
      "link": "http://novatoscript.pythonanywhere.com/"
    },
    {
      "sn": 7,
      "projectTitle": "FollowScreen",
      "periodStart": "Jul 2016",
      "periodEnd": "Jul 2016",
      "toolsUsed": [
        "python",
        "pyautogui",
        "tkinter"
      ],
      "tags": [
        "screen-recording",
        "python",
        "autmation"
      ],
      "shortInfo": "Its a screen recorder written in python. It records the screen activities.I used PyAutoGUI and PIL modules for this.Audio capturing is yet to be added.",
      "link": "https://github.com/moghya/followscreen"
    },
    {
      "sn": 8,
      "projectTitle": "Digital Library Portal",
      "periodStart": "Feb 2017",
      "periodEnd": "May 2017",
      "toolsUsed": [
        "QuilJs",
        "php",
        "mysql",
        "JavaScript"
      ],
      "tags": [
        "webapp",
        "php",
        "mysql",
        "js",
        "materialize"
      ],
      "shortInfo": "According to the requirements taken Developed a Digital Library Portal for College Library. All of the sections are dynamic and everything is editable using Admin Panel. Used Quill-Js for implementing Editor for Admin. PHP, MySQL is used.",
      "link": "#"
    },
    {
      "sn": 5,
      "projectTitle": "Book Bank Allotment System",
      "periodStart": "Jan 2017",
      "periodEnd": "May 2017",
      "toolsUsed": [
        "php",
        "mongodb",
        "js"
      ],
      "tags": [
        "mongodb",
        "nosql",
        "php"
      ],
      "shortInfo": "Developed a Web Application using PHP and MongoDB for Book Bank Allotment done by AGCL library of WCE, Sangli. Automated process of Allocation, it was done manually and use to take almost 15-20 days for completion. Our system does it in a single day.",
      "link": "#"
    },
    {
      "sn": 4,
      "projectTitle": "Detection and Prevention of Black hole Attack in MANET",
      "periodStart": "Jul 2016",
      "periodEnd": "Nov 2016",
      "toolsUsed": [
        "c++",
        "ns2",
        "tcl",
        "awk"
      ],
      "tags": [
        "c++",
        "blackhole-attack",
        "ns2"
      ],
      "shortInfo": "It was a Team Project. We made changes in AODV protocol to simulate Black hole attack in Mobile and Adhoc Network​ and later implemented techniques for prevention of the Attack.",
      "link": "#"
    },
    {
      "sn": 10,
      "projectTitle": "JNV Washim Alumni Portal",
      "periodStart": "Dec 2015",
      "periodEnd": "Jan 2016",
      "toolsUsed": [
        "php",
        "mysql",
        "js"
      ],
      "tags": [
        "webapp",
        "php",
        "mysql",
        "js"
      ],
      "shortInfo": "Developed a Web Application for Alumni Portal of Jawahar Navodaya Vidyalaya,Washim. It's developed using PHP, HTML, CSS,JavaScript, Bootstrap. All out of scratch. We used MySQL database . Alumni of JNV Washim have to register here with there details and we can searchfor Alumnus with filters.",
      "link": "http://www.jnvwashimalumni.org/"
    },
    {
      "sn": 6,
      "projectTitle": "toGithub",
      "periodStart": "May 2017",
      "periodEnd": "Present",
      "toolsUsed": [
        "python",
        "PyGithub",
        "requests",
        "beautifulsoup"
      ],
      "tags": [
        "scraping",
        "git-api"
      ],
      "shortInfo": "A python app developed for scraping solutions from Sport Programming Websites and uploding them to Github.",
      "link": "https://github.com/moghya/toGithub"
    }
  ],
  "summary": "<p>Hello, I'm a Computer science enthusiast and B.Tech Information Technology graduate having 2 years of experience as Software Development Engineer in Internet/Ad-Tech industry. As of now I'm involved in developing distributed system software for Storage Management.</p>\n\n<p>I'm passionate about programming and delivering, clean, test-covered, well-designed and scalable code. I seek to learn and try to apply all of it in a way that makes life easier. I always try to design, develop and deliver technology solutions to problems around me.</p>",
  "profileLinks": [
    {
      "name": "Github",
      "icon": "github.svg",
      "link": "https://github.com/moghya",
      "sn": 2
    },
    {
      "name": "LinkedIn",
      "icon": "linkedin.svg",
      "link": "https://www.linkedin.com/in/shubham-sawant-67074a86/",
      "sn": 1
    },
    {
      "name": "Medium",
      "icon": "medium.svg",
      "link": "https://medium.com/howcatcancode",
      "sn": 5
    },
    {
      "name": "StackOverflow",
      "icon": "stack-overflow.png",
      "link": "https://stackoverflow.com/users/5186709/moghya",
      "sn": 3
    },
    {
      "name": "Twitter",
      "icon": "twitter.svg",
      "link": "https://twitter.com/moghya",
      "sn": 4
    }
  ],
  "likes": [
    {
      "name": "Programming",
      "icon": "programming.svg",
      "sn": 1
    },
    {
      "name": "Maths",
      "icon": "maths.svg",
      "sn": 2
    },
    {
      "name": "Armed Forces",
      "icon": "soldier.svg",
      "sn": 3
    },
    {
      "name": "Reading",
      "icon": "book.svg",
      "sn": 4
    },
    {
      "name": "Singing",
      "icon": "singer.svg",
      "sn": 5
    },
    {
      "name": "Watermelon",
      "icon": "watermelon.svg",
      "sn": 6
    },
    {
      "name": "Chicken",
      "icon": "chicken.svg",
      "sn": 7
    },
    {
      "name": "Cycling",
      "icon": "cycling.svg",
      "sn": 8
    },
    {
      "name": "Trekking",
      "icon": "trek.svg",
      "sn": 9
    },
    {
      "name": "Camping",
      "icon": "tent.svg",
      "sn": 10
    }
  ],
  "qoutes": [
    "Your death is something that happens to everyone else.",
    "You only live as long as the last person who remembers you.",
    "Every day every hour turn the pain into power.",
    "If you cannot be a pencil to write someone's happiness, then try to be an erases to erase someone's sorrows.",
    "Tabs are better than spaces."
  ],
  "helloText": "<p>Dear Visitor, Thank you for visiting my webspace.</p>\n<p>I'm working as Member of Technical Staff at <a href='https://cohesity.com'>Cohesity</a></p>\n<p>Before this I used work as Software Development Engineer at <a href='http://media.net'>Media.Net</a>. I completed  B.Tech Information Technology at <a href='http://walchandsangli.ac.in'>Walchand College of Engineering Sangli</a> and my schooling from <a href='http://jnvwashim.gov.in'>Jawahar Navodaya Vidyalaya, Washim</a>.</p>\n\n<p>I'm interested in Algorithms, System Programming, Distributed Systems and Machine Learning. I overwhelmingly like C++, Python and Javascript :)</p>\n\n<p>How can I help you?</br>I can design, develop and deliver technological solutions to your problems.</p><p>Do we have something in common? If yes, let's have a talk about it and grow together.</p> <p> We don't have anything in common?</br>That's fine,please introduce me something that I'm missing.</p>"
}
