{
	"personalInfo": {
		"myimg": "image.jpg",
		"fname": "Shubham",
		"mname": "Parashram",
		"lname": "Sawant",
		"nick":"moghya",
		"address": {
			"list": ["Gupta Layout, Mahakali road, Washim, District-Washim, Maharashtra, India 444505 ",
				"'OM' Jaihind colony, Vishrambag, Sangli District-Sangli, Maharashtra, India 416415"
			]
		},
		"email": "sawantshubham571@gmail.com",
		"mob": "+919881464434"
	},
	"educations": [
		{

			"periodStart": "July 2014",
			"periodEnd": "May 2018",
			"course": "B.Tech Information Technology",
			"score": "7.36 CGPA",
			"inst": "Walchand College of Engineering, Sangli",
			"board": "Shivaji University",
			"courses": [
				{
					"courseCode": "3IT202",
					"courseName": "Data Structures",
					"courseScore": "9/10",
					"sn": 1

				},
				{
					"courseCode": "3IT304",
					"courseName": "Computer Algorithms",
					"courseScore": "7/10",
					"sn": 2

				},
				{
					"courseCode": "3IT331",
					"courseName": "Machine Learning",
					"courseScore": "10/10",
					"sn": 3

				},
				{
					"courseCode": "3OE---",
					"courseName": "Data Analytics",
					"courseScore": "8/10",
					"sn": 4

				},
				{
					"courseCode": "3IT211",
					"courseName": "Theory of Computation",
					"courseScore": "8/10",
					"sn": 5

				},
				{
					"courseCode": "3IT201",
					"courseName": "Discrete Mathemactics",
					"courseScore": "7/10",
					"sn": 6

				},
				{
					"courseCode": "3IT303",
					"courseName": "Operating System",
					"courseScore": "8/10",
					"sn": 10

				},
				{
					"courseCode": "3IT322",
					"courseName": "Unix Operating System",
					"courseScore": "8/10",
					"sn": 11

				},
				{
					"courseCode": "3IT301",
					"courseName": "Database Engineering",
					"courseScore": "9/10",
					"sn": 12

				},
				{
					"courseCode": "3IT321",
					"courseName": "Advanced Database Engineering",
					"courseScore": "9/10",
					"sn": 13

				},
				{
					"courseCode": "3IT204",
					"courseName": "Data Communication and Networking",
					"courseScore": "7/10",
					"sn": 15

				},
				{
					"courseCode": "3IT213",
					"courseName": "Computer and Wireless Networks",
					"courseScore": "6/10",
					"sn": 16

				},
				{
					"courseCode": "3IT263",
					"courseName": "Computer and Wireless Networks Lab",
					"courseScore": "8/10",
					"sn": 34

				},
				{
					"courseCode": "3IT212",
					"courseName": "Computer Organization and Architechture",
					"courseScore": "7/10",
					"sn": 18

				},
				{
					"courseCode": "3IT372",
					"courseName": "Parallel Programming Lab",
					"courseScore": "10/10",
					"sn": 32

				},
				{
					"courseCode": "3IT324",
					"courseName": "Information Storage and Management",
					"courseScore": "6/10",
					"sn": 21

				},
				{
					"courseCode": "3MA204",
					"courseName": "Linear Algebra",
					"courseScore": "7/10",
					"sn": 7

				},
				{
					"courseCode": "3MA215",
					"courseName": "Statistics and Fuzzy Systems",
					"courseScore": "6/10",
					"sn": 8

				},
				{
					"courseCode": "3IT252",
					"courseName": "Data Structures Lab",
					"courseScore": "10/10",
					"sn": 29

				},
				{
					"courseCode": "3IT203",
					"courseName": "Processor Architechture",
					"courseScore": "7/10",
					"sn": 17


				},
				{
					"courseCode": "3IT281",
					"courseName": "Mini Project - I",
					"courseScore": "10/10",
					"sn": 22

				},
				{
					"courseCode": "3IT214",
					"courseName": "System Programming",
					"courseScore": "7/10",
					"sn": 19

				},
				{
					"courseCode": "3IT255",
					"courseName": "Programming Lab - I (C++)",
					"courseScore": "10/10",
					"sn": 26

				},
				{
					"courseCode": "3IT352",
					"courseName": "Web Technology Lab",
					"courseScore": "9/10",
					"sn": 33

				},
				{
					"courseCode": "3IT342",
					"courseName": "Mini Project - IV",
					"courseScore": "10/10",
					"sn": 25

				},
				{
					"courseCode": "3IT341",
					"courseName": "Mini-Project - III",
					"courseScore": "10/10",
					"sn": 24

				},
				{
					"courseCode": "3IT302",
					"courseName": "Software Engineering Design",
					"courseScore": "7/10",
					"sn": 20

				},
				{
					"courseCode": "3IT371",
					"courseName": "Unix Operating System Lab",
					"courseScore": "10/10",
					"sn": 30

				},
				{
					"courseCode": "3IT282",
					"courseName": "Mini Project - II",
					"courseScore": "10/10",
					"sn": 23

				},
				{
					"courseCode": "3IT265",
					"courseName": "Programming Lab - II (Java)",
					"courseScore": "10/10",
					"sn": 27

				},
				{
					"courseCode": "3IT312",
					"courseName": "Cloud Computing",
					"courseScore": "7/10",
					"sn": 14

				},
				{
					"courseCode": "3IT323",
					"courseName": "Information Theory",
					"courseScore": "8/10",
					"sn": 9

				},
				{
					"courseCode": "2IT253",
					"courseName": "Processor Architechture Lab",
					"courseScore": "10/10",
					"sn": 28

				},
				{
					"courseCode": "3IT351",
					"courseName": "Database Engineering Lab",
					"courseScore": "10/10",
					"sn": 31

				}
			]
		},
		{

			"periodStart": "April 2013",
			"periodEnd": "May 2014",
			"course": "All India Senior School Examination",
			"score": "89.4%",
			"inst": "Jawahar Navodaya Vidyalaya,Washim",
			"board": "CBSE Chennai",
			"courses": [{
					"courseCode": "041",
					"courseName": "Mathemactics",
					"courseScore": "86/100",
					"sn": 1
				},
				{
					"courseCode": "042",
					"courseName": "Physics",
					"courseScore": "87/100",
					"sn": 2
				},
				{
					"courseCode": "043",
					"courseName": "Chemistry",
					"courseScore": "86/100",
					"sn": 3
				},
				{
					"courseCode": "083",
					"courseName": "Computer Science",
					"courseScore": "94/100",
					"sn": 4
				}
			]
		},
		{

			"periodStart": "April 2011",
			"periodEnd": "May 2012",
			"course": "All India Secondary School Examination",
			"score": "10.00 CGPA",
			"inst": "Jawahar Navodaya Vidyalaya,Washim",
			"board": "CBSE Chennai",
			"courses": [{
					"courseCode": "041",
					"courseName": "Mathemactics",
					"courseScore": "10/10",
					"sn": 1
				},
				{
					"courseCode": "086",
					"courseName": "Science",
					"courseScore": "10/10",
					"sn": 2
				}
			]
		}
	],
	"skills": [
		{
			"sn": 1,
			"name": "C++",
			"icon": ""
		},
		{
			"sn": 2,
			"name": "Python",
			"icon": ""
		},
		{
			"sn": 3,
			"name": "JavaScript",
			"icon": ""
		},
		{
			"sn": 4,
			"name": "PHP",
			"icon": ""
		},
		{
			"sn": 5,
			"name": "MySQL",
			"icon": ""
		},
		{
			"sn": 6,
			"name": "MongoDB",
			"icon": ""
		},
		{
			"sn": 7,
			"name": "Apache",
			"icon": ""
		},
		{
			"sn": 8,
			"name": "Git",
			"icon": ""
		},
		{
			"sn": 9,
			"name": "Django",
			"icon": ""
		},
		{
			"sn": 10,
			"name": "Ubuntu",
			"icon": ""
		},
		{
			"sn":11,
			"name":"HTML5",
			"icon":""
		},
		{
			"sn":12,
			"name":"jQuery",
			"icon":""
		},
		{
			"sn":13,
			"name":"CSS3",
			"icon":""
		},
		{
			"sn":14,
			"name":"Bootstrap",
			"icon":""
		},
		{
			"sn":15,
			"name":"Heroku",
			"icon":""
		},
		{
			"sn":16,
			"name":"Flask",
			"icon":""
		}
	],
	"works": [
		{
			"sn":6,"link":"","workPosition": "Scout Troop Leader",
			"periodStart": "April 2010",
			"periodEnd": "May 2012",
			"organisation": "JNV,Washim",
			"experience": "It was nice to be a part of Scouting.Arranged camps,hikes and awareness rallies."
		},
		{
			"sn":5,"link":"http://wcepace.in/","workPosition": "Asst. Program Director in Events",
			"periodStart": "April 2015",
			"periodEnd": "March 2016",
			"organisation": "Personality Advancement Circle of Engineers.",
			"experience": "Learnt how to organize professional events and actvites, how to manage resources and make most out of everything."
		},
		{
			"sn":4,"link":"http://wcepace.in/","workPosition": "Joint. Skills Developer",
			"periodStart": "April 2016",
			"periodEnd": "January 2017",
			"organisation": "Personality Advancement Circle of Engineers.",
			"experience": "Good to arrange Meet ups for professional skill development of fellow PACErs."
		},
		{
			"sn":3,"link":"http://wcepace.in/","workPosition": "Cheif. Skills Developer",
			"periodStart": "January 2017",
			"periodEnd": "Present",
			"organisation": "Personality Advancement Circle of Engineers.",
			"experience": "Good to arrange Meet ups for professional skill development of fellow PACErs."
		},
		{
			"sn":2,"link":"http://pitchteq.com/","workPosition": "Lead PHP Developer",
			"periodStart": "July 2016",
			"periodEnd": "Present",
			"organisation": "PitchTeQ ",
			"experience": "A group of college students established a web solutions startup. Worked on an e-commerce project."
		},
		{
			"sn":1,"link":"http://www.praxisinfotech.com/","workPosition": "Web Development Intern",
			"periodStart": "June 2017",
			"periodEnd": "Present",
			"organisation": "Praxis Infotech ",
			"experience": "Joined Praxis under TIFAC scheme. Working on a business app using goole map apis."
		}
	],
	"projects":[
		{

			"sn":14, "projectTitle": "Traffic Rules",
			"periodStart": "July 2015",
			"periodEnd": "Nov 2015",
			"toolsUsed": ["Blender", "Movie Maker"],
			"tags": ["blender", "animation", "3d-modelling", "traffic rules"],
			"shortInfo": "Its a 3D animation video made using Blender Tool for spreading awareness regarding Traffic rules. Mini project for semester III.",
			"link":"https://github.com/moghya/Traffic-Rules"
		},
		{
			"sn":13, "projectTitle": "Smart Hospital Management",
			"periodStart": "Aug 2015",
			"periodEnd": "Sep 2015",
			"toolsUsed": ["c++", "qt"],
			"tags": ["oop", "c++", "qt", "gui", "files"],
			"shortInfo": "C++ Qt Standalone Application keeps track of every patient and its visits. Data collected can be used for Projects of Data Mining and Machine Learning as data sets.",
			"link":"https://github.com/moghya/smartHMS"
		},
		{
			"sn":12, "projectTitle": "Seat Allocation",
			"periodStart": "Dec 2015",
			"periodEnd": "Dec 2015",
			"toolsUsed": ["c++"],
			"tags": ["c++", "gayle-shapely", "ds", "oop"],
			"shortInfo": "Simulation of college seat allocation process. Choice filling and Seat Allocation are performed. Modified Gayle-Shapely Algorithm implemented. Can be scaled using C++ CGI for deployment.",
			"link":"https://github.com/moghya/collegeSeatAllocationPrototype"
		},
		{
			"sn":11, "projectTitle": "Online External Examination Portal",
			"periodStart": "Feb 2016",
			"periodEnd": "May 2016",
			"toolsUsed": ["php", "js", "mysql", "html", "css", "bootstrap"],
			"tags": ["php", "js", "bootstrap", "mysql"],
			"shortInfo": "It's a web application developed using PHP , MySQL, Bootstrap, JavaScript etc. for conducting practical exams online.",
			"link":"https://github.com/moghya/external-exam-portal"
		},
		{
			"sn":9, "projectTitle": "LookIn",
			"periodStart": "Mar 2016",
			"periodEnd": "May 2016",
			"toolsUsed": ["python", "sqllite3", "beautifulsoup", "requests"],
			"tags": ["search engine", "python", "indexing", "web scraping"],
			"shortInfo": "It's a search engine made using Python, Beautifulsoup . Which crawls downloaded websites and indexes them. After one time indexing it delivers search results ",
			"link":""
		},
		{
			"sn":3, "projectTitle": "dsalglib ",
			"periodStart": "May 2016",
			"periodEnd": "Present",
			"toolsUsed": ["c++"],
			"tags": ["ds", "algo", "template", "c++"],
			"shortInfo": "Its a ready to use data structures and algorithms c++ template library.Many useful data structures and algorithms are implemented . One should just focus on his/her project necessity and dsalglib will take care of data structures and algorithms.",
			"link":"http://moghya.me/dsalglib/"
		},
		{
			"sn":1, "projectTitle": "Strategic Location using Facebook Data",
			"periodStart": "Dec 2016",
			"periodEnd": "Dec 2016",
			"toolsUsed": ["python","scikit-learn","ipynb","graph-api"],
			"tags": ["machine-learning","regression","python"],
			"shortInfo": "Choosing optimal location for business using data from social media websites contribute largely to the profit.Our System helps business choose optimal location for higher number of check-ins .indirectly helping businesses to increase their profits.We have used to machine learning techniques to help improve our system.",
			"link":""
		},
		{
			"sn":2, "projectTitle": "prowessIndex",
			"periodStart": "June 2017",
			"periodEnd": "June 2017",
			"toolsUsed": ["python","flask","pandas"],
			"tags": ["python","data analytics"],
			"shortInfo": "This is a simple flask web app implementation of a paper that I'm writing 'Making Sense of Numbers'. This paper proposes method for deriving inferences about prowessness of a stduent using attained graded.",
			"link":"http://novatoscript.pythonanywhere.com/"
		},
		{
			"sn":7, "projectTitle": "FollowScreen",
			"periodStart": "Jul 2016",
			"periodEnd": "Jul 2016",
			"toolsUsed": ["python","pyautogui","tkinter"],
			"tags": ["screen-recording","python","autmation"],
			"shortInfo": "Its a screen recorder written in python. It records the screen activities.I used PyAutoGUI and PIL modules for this.Audio capturing is yet to be added.",
			"link":"https://github.com/moghya/followscreen"
		},
		{
			"sn":8, "projectTitle": "Digital Library Portal",
			"periodStart": "Feb 2017",
			"periodEnd": "May 2017",
			"toolsUsed": ["QuilJs","php","mysql","JavaScript"],
			"tags": ["webapp","php","mysql","js","materialize"],
			"shortInfo": "According to the requirements taken Developed a Digital Library Portal for College Library. All of the sections are dynamic and everything is editable using Admin Panel. Used Quill-Js for implementing Editor for Admin. PHP, MySQL is used.",
			"link":"#"
		},
		{
			"sn":5, "projectTitle": "Book Bank Allotment System",
			"periodStart": "Jan 2017",
			"periodEnd": "May 2017",
			"toolsUsed": ["php","mongodb","js"],
			"tags": ["mongodb","nosql","php"],
			"shortInfo": "Developed a Web Application using PHP and MongoDB for Book Bank Allotment done by AGCL library of WCE, Sangli. Automated process of Allocation, it was done manually and use to take almost 15-20 days for completion. Our system does it in a single day.",
			"link":"#"
		},
		{
			"sn":4, "projectTitle": "Detection and Prevention of Black hole Attack in MANET",
			"periodStart": "Jul 2016",
			"periodEnd": "Nov 2016",
			"toolsUsed": ["c++","ns2","tcl","awk"],
			"tags": ["c++","blackhole-attack","ns2"],
			"shortInfo": "It was a Team Project. We made changes in AODV protocol to simulate Black hole attack in Mobile and Adhoc Network​ and later implemented techniques for prevention of the Attack.",
			"link":"#"
		},
		{
			"sn":10, "projectTitle": "JNV Washim Alumni Portal",
			"periodStart": "Dec 2015",
			"periodEnd": "Jan 2016",
			"toolsUsed": ["php","mysql","js"],
			"tags": ["webapp","php","mysql","js"],
			"shortInfo": "Developed a Web Application for Alumni Portal of Jawahar Navodaya Vidyalaya,Washim. It's developed using PHP, HTML, CSS,JavaScript, Bootstrap. All out of scratch. We used MySQL database . Alumni of JNV Washim have to register here with there details and we can searchfor Alumnus with filters.",
			"link":"http://www.jnvwashimalumni.org/"
		},
		{
			"sn":6, "projectTitle": "toGithub",
			"periodStart": "May 2017",
			"periodEnd": "Present",
			"toolsUsed": ["python","PyGithub","requests","beautifulsoup"],
			"tags": ["scraping","git-api"],
			"shortInfo": "A python app developed for scraping solutions from Sport Programming Websites and uploding them to Github.",
			"link":"https://github.com/moghya/toGithub"
		}
	],
	"summary": "Hi, I’m Shubham. I believe in Maths. I seek to learn and try to apply all that I learn in a way that makes life easier. I can design and develop technology solutions. Mathematics, Algorithms, Data Structures  and Machine Learning are my areas of Interest. I'm looking for an Internship where I can learn and grow by using my tech skills and make this world a better place.",
	"profileLinks": [
		{
			"name": "Facebook",
			"icon": "",
			"link": "https://www.facebook.com/moghya",
			"sn":9
		},
		{
			"name": "Github",
			"icon": "",
			"link": "https://github.com/moghya",
			"sn":1
		},
		{
			"name": "LinkedIn",
			"icon": "",
			"link": "https://www.linkedin.com/in/shubham-sawant-67074a86/",
			"sn":2
		},
		{
			"name": "Codeforces",
			"icon": "",
			"link": "http://codeforces.com/profile/sawant",
			"sn":3
		},
		{
			"name": "Codechef",
			"icon": "codechef.png",
			"link": "https://www.codechef.com/users/moghya",
			"sn":4
		},
		{
			"name": "Hackerrank",
			"icon": "",
			"link": "https://www.hackerrank.com/moghya",
			"sn":5
		},
		{
			"name": "Hackerearth",
			"icon": "hackerearth.png",
			"link": "https://www.hackerearth.com/@moghya",
			"sn":6
		},
		{
			"name": "Medium",
			"icon": "",
			"link": "https://medium.com/howcatcancode",
			"sn":7
		},	
		{
			"name": "Quora",
			"icon": "",
			"link": "https://www.quora.com/profile/Shubham-Sawant-5",
			"sn":8
		},	
		{
			"name": "Twitter",
			"icon": "",
			"link": "https://twitter.com/moghya",
			"sn":10
		}
	],
	"likes":[
		{
			"name":"Programming",
			"icon":"",
			"sn":1
		},
		{
			"name":"Maths",
			"icon":"",
			"sn":2
		},
		{
			"name":"Armed Forces",
			"icon":"",
			"sn":3
		},
		{
			"name":"Reading",
			"icon":"",
			"sn":4
		},
		{
			"name":"Singing",
			"icon":"",
			"sn":5
		},
		{
			"name":"Watermelon",
			"icon":"",
			"sn":6
		},
		{
			"name":"Chicken",
			"icon":"",
			"sn":7
		},
		{
			"name":"Cycling",
			"icon":"",
			"sn":8
		},
		{
			"name":"Trekking",
			"icon":"",
			"sn":9
		},
		{
			"name":"Camping",
			"icon":"",
			"sn":10
		}

	],
	"qoutes": [
		"If you cannot be a pencil to write someone's happiness, then try to be an erases to erase someone's sorrows.",
		"Tabs are better than spaces."
	],
	"helloText":"<p>Thanks for visiting my webspace.</p><p>Currently I'm studying B.Tech Information Technology  at Walchand College of Engineering Sangli. I do Web development, Machine Learning and Computer Algorithms.I overwhelmingly like C++, Python and Javascript :)</p><p>How can I help you ?</br>I can design, develop and deliver technological solutions to your problems.</p><p>Do we have something in common ?</br>Let's have a talk about it and grow together.</br> We don't have anything in common ?</br>Oh then that's great, please introduce me something that I'm missing.</p>"
}
